{
  "sortParamsByRequiredFlag": "true",
  "ensureUniqueParams": "true",
  "allowUnicodeIdentifiers": "true",
  "modelPackage": "Model",
  "apiPackage": "Api",
  "variableNamingConvention": "camelCase",
  "invokerPackage": "Interserver\\Mailbaby",
  "packagePath": "",
  "srcBasePath": "src",
  "gitUserId": "interserver",
  "gitRepoId": "mailbaby-client-php",
  "composerVendorName": "interserver",
  "composerProjectName": "mailbaby-client-php",
  "artifactVersion": "1.0.0",
  "hideGenerationTimestamp": "true"
}
